{
  "schema_version": 2,
  "cases": [
    {
      "paper_id": "1803.01876",
      "title": "Edge states and topological invariants of non-Hermitian systems",
      "topic": "Non-Hermitian SSH model and non-Bloch bulk-boundary correspondence",
      "preprint": {
        "identifier": "arXiv:1803.01876",
        "title": "Edge states and topological invariants of non-Hermitian systems",
        "url": "https://arxiv.org/abs/1803.01876"
      },
      "publication": {
        "status": "published",
        "title": "Edge States and Topological Invariants of Non-Hermitian Systems",
        "venue": "Physical Review Letters",
        "citation": "Physical Review Letters 121, 086803 (2018)",
        "doi": "10.1103/PhysRevLett.121.086803",
        "doi_url": "https://doi.org/10.1103/PhysRevLett.121.086803",
        "locator": "086803"
      },
      "status": "Paper-parameter complete reproduction",
      "similarity_level": "complete_reproduction",
      "audit_score": 94.0,
      "summary": "Reproduces the open-boundary spectrum, generalized Brillouin zone, skin profiles, non-Bloch winding, and the nonzero-t3 extension.",
      "limitation": "Author plotting data are unavailable; digitized source references were used internally for validation but are not redistributed.",
      "run_scripts": [
        "run_fig2_open_spectrum.py",
        "run_fig3_beta_skin.py",
        "run_fig4_winding.py",
        "run_fig5_t3.py"
      ],
      "featured_results": [
        {
          "paper_item": "Fig. 2",
          "result": "Open-boundary spectrum and zero-mode interval",
          "figure": "fig2_open_spectrum.png",
          "check": "fig2_open_spectrum.json"
        },
        {
          "paper_item": "Fig. 3",
          "result": "Beta roots, generalized Brillouin zone, and skin profiles",
          "figure": "fig3_beta_skin.png",
          "check": "fig3_beta_skin.json"
        },
        {
          "paper_item": "Fig. 4",
          "result": "Non-Bloch winding plateau",
          "figure": "fig4_winding.png",
          "check": "fig4_winding.json"
        },
        {
          "paper_item": "Fig. 5",
          "result": "Paper-parameter nonzero-t3 spectrum, winding, and noncircular GBZ",
          "figure": "fig5_t3.png",
          "check": "fig5_t3.json"
        }
      ],
      "comparison_attribution": "Yao and Wang",
      "comparison_results": [
        {
          "paper_item": "Fig. 2",
          "figure": "fig2_open_spectrum_comparison.png"
        },
        {
          "paper_item": "Fig. 2(d)",
          "figure": "fig2d_boundary_perturbation_comparison.png"
        },
        {
          "paper_item": "Fig. 3",
          "figure": "fig3_beta_skin_comparison.png"
        },
        {
          "paper_item": "Fig. 4",
          "figure": "fig4_winding_comparison.png"
        },
        {
          "paper_item": "Fig. 5",
          "figure": "fig5_t3_comparison.png"
        },
        {
          "paper_item": "Supplemental Fig. 1",
          "figure": "figs1_complex_spectra_comparison.png"
        },
        {
          "paper_item": "Supplemental Fig. 2",
          "figure": "figs2_gamma24_comparison.png"
        }
      ],
      "extra_dependencies": [
        "mpmath"
      ]
    },
    {
      "paper_id": "1804.04672",
      "title": "Non-Hermitian Chern bands",
      "topic": "Non-Hermitian Chern bands and non-Bloch Chern physics",
      "preprint": {
        "identifier": "arXiv:1804.04672",
        "title": "Non-Hermitian Chern bands",
        "url": "https://arxiv.org/abs/1804.04672"
      },
      "publication": {
        "status": "published",
        "title": "Non-Hermitian Chern Bands",
        "venue": "Physical Review Letters",
        "citation": "Physical Review Letters 121, 136802 (2018)",
        "doi": "10.1103/PhysRevLett.121.136802",
        "doi_url": "https://doi.org/10.1103/PhysRevLett.121.136802",
        "locator": "136802"
      },
      "status": "Feature-level reproduction",
      "similarity_level": "numerical_feature_reproduction",
      "audit_score": 80.18,
      "summary": "Reproduces open-boundary and cylinder phase structure, square dynamics, complex spectra, and finite-size checks.",
      "limitation": "Some phase-boundary and panel-level comparisons remain paper-subset or source-table validations rather than full independent finite-size reruns.",
      "run_scripts": [
        "run_first_target.py",
        "run_open_boundary_phase_diagram.py",
        "run_square_dynamics.py",
        "run_cylinder_phase_diagram.py",
        "run_gap_scaling.py",
        "run_disk_phase_diagram.py"
      ],
      "extra_dependencies": [],
      "comparison_attribution": "Yao et al.",
      "comparison_results": [
        {
          "paper_item": "Fig. 1",
          "figure": "fig1_open_boundary_phase_comparison.png"
        },
        {
          "paper_item": "Fig. 2",
          "figure": "fig2_square_dynamics_comparison.png"
        },
        {
          "paper_item": "Fig. 3(a)",
          "figure": "fig3a_cylinder_phase_comparison.png"
        },
        {
          "paper_item": "Fig. 3(b)",
          "figure": "fig3b_complex_spectrum_comparison.png"
        },
        {
          "paper_item": "Fig. S2",
          "figure": "figs2_gap_scaling_comparison.png"
        },
        {
          "paper_item": "Fig. S3",
          "figure": "figs3_disk_phase_comparison.png"
        }
      ]
    },
    {
      "paper_id": "10.1145-3297858.3304023",
      "title": "Tackling the Qubit Mapping Problem for NISQ-Era Quantum Devices",
      "topic": "SABRE qubit mapping and routing",
      "preprint": {
        "identifier": "arXiv:1809.02573",
        "title": "Tackling the Qubit Mapping Problem for NISQ-Era Quantum Devices",
        "url": "https://arxiv.org/abs/1809.02573"
      },
      "publication": {
        "status": "published",
        "title": "Tackling the Qubit Mapping Problem for NISQ-Era Quantum Devices",
        "venue": "ASPLOS '19",
        "citation": "ASPLOS '19, pp. 1001–1014",
        "doi": "10.1145/3297858.3304023",
        "doi_url": "https://doi.org/10.1145/3297858.3304023",
        "locator": "1001–1014"
      },
      "status": "Full-corpus mechanism reproduction",
      "similarity_level": "numerical_feature_reproduction",
      "audit_score": 68.29,
      "summary": "Reconstructs the SABRE routing pipeline, swap trace, reverse traversal, decay trade-off, and all 26 rows of Table II. Row-exact optimized values remain limited by unpublished run metadata.",
      "limitation": "All 26 Table II rows run and produce hardware-compliant routes, but row-exact optimized values require the paper's unpublished random seeds, tie-breaking order, and BKA post-processing inputs. This is a metadata boundary, not a compute boundary.",
      "run_scripts": [
        "run_paper_swap_example.py",
        "run_core_benchmarks.py",
        "run_decay_tradeoff.py"
      ],
      "extra_dependencies": [
        "networkx",
        "qiskit"
      ],
      "comparison_attribution": "Li et al.",
      "comparison_results": [
        {
          "paper_item": "Table 2",
          "figure": "table2_gop_comparison.png"
        }
      ]
    },
    {
      "paper_id": "1608.02589",
      "title": "Discrete time crystals: rigidity, criticality, and realizations",
      "topic": "Floquet many-body dynamics and discrete time crystals",
      "preprint": {
        "identifier": "arXiv:1608.02589",
        "title": "Discrete time crystals: rigidity, criticality, and realizations",
        "url": "https://arxiv.org/abs/1608.02589"
      },
      "publication": {
        "status": "published",
        "title": "Discrete Time Crystals: Rigidity, Criticality, and Realizations",
        "venue": "Physical Review Letters",
        "citation": "Physical Review Letters 118, 030401 (2017)",
        "doi": "10.1103/PhysRevLett.118.030401",
        "doi_url": "https://doi.org/10.1103/PhysRevLett.118.030401",
        "locator": "030401"
      },
      "status": "Medium-scale partial reproduction",
      "similarity_level": "numerical_feature_reproduction",
      "audit_score": 73.56,
      "summary": "Reproduces subharmonic rigidity, level statistics, variance, long-range variance, and mutual-information features with exact local evolution.",
      "limitation": "The published medium campaign aggregates 168 jobs into 55 paper-parameter points at L=8,10,12. The final L=8,10,12,14 high-statistics campaign was not launched; optional L=16,18 also require a memory-aware eigensolver.",
      "run_scripts": [
        "run_reproduction.py",
        "plot_reproduction.py",
        "run_reproduction_iteration2.py",
        "plot_reproduction_iteration2.py",
        "extract_fig3_scaling_collapse.py"
      ],
      "extra_dependencies": [],
      "comparison_attribution": "Yao et al.",
      "comparison_results": [
        {
          "paper_item": "Fig. 1",
          "figure": "fig1_subharmonic_rigidity_comparison.png"
        },
        {
          "paper_item": "Fig. 2",
          "figure": "fig2_level_statistics_comparison.png"
        },
        {
          "paper_item": "Fig. 3(a)",
          "figure": "fig3_mutual_information_comparison.png"
        },
        {
          "paper_item": "Fig. 3(b-d)",
          "figure": "fig3_scaling_collapse_comparison.png"
        },
        {
          "paper_item": "Fig. 4",
          "figure": "fig4_long_range_variance_comparison.png"
        }
      ]
    },
    {
      "paper_id": "1711.03528",
      "title": "Quantum many-body scars",
      "topic": "PXP dynamics and quantum many-body scars",
      "preprint": {
        "identifier": "arXiv:1711.03528",
        "title": "Quantum many-body scars",
        "url": "https://arxiv.org/abs/1711.03528"
      },
      "publication": {
        "status": "published",
        "title": "Weak ergodicity breaking from quantum many-body scars",
        "venue": "Nature Physics",
        "citation": "Nature Physics 14, 745–749 (2018)",
        "doi": "10.1038/s41567-018-0137-5",
        "doi_url": "https://doi.org/10.1038/s41567-018-0137-5",
        "locator": "745–749"
      },
      "status": "Symmetry-resolved partial reproduction",
      "similarity_level": "numerical_feature_reproduction",
      "audit_score": 72.5,
      "summary": "Reproduces constrained Hilbert-space structure, scar overlaps, revivals, participation ratios, and symmetry-resolved level statistics.",
      "limitation": "The paper's k=0, I=+1 sector is reproduced at L=28 (dimension 13201), including the 15-state scar tower. L=32 is not launched because one float64 dense matrix is already about 47 GB before eigensolver workspace on the current 40 GB A100 path; thermodynamic-limit iTEBD also remains unimplemented.",
      "run_scripts": [
        "run_reproduction.py",
        "plot_reproduction.py",
        "run_symmetry_resolved_sector.py",
        "plot_symmetry_resolved_sector.py"
      ],
      "extra_dependencies": [],
      "comparison_attribution": "Turner et al.",
      "comparison_results": [
        {
          "paper_item": "Fig. 1",
          "figure": "fig1_pxp_hilbert_graph_comparison.png"
        },
        {
          "paper_item": "Fig. 2",
          "figure": "fig2_scar_special_states_comparison.png"
        },
        {
          "paper_item": "Fig. 3",
          "figure": "fig3_quench_entanglement_dynamics_comparison.png"
        },
        {
          "paper_item": "Fig. 4",
          "figure": "fig4_level_statistics_comparison.png"
        }
      ]
    },
    {
      "paper_id": "2103.03074",
      "title": "Simulating the Sycamore quantum supremacy circuits",
      "topic": "Sycamore random-circuit simulation",
      "preprint": {
        "identifier": "arXiv:2103.03074",
        "title": "Simulating the Sycamore quantum supremacy circuits",
        "url": "https://arxiv.org/abs/2103.03074"
      },
      "publication": {
        "status": "published",
        "title": "Simulation of Quantum Circuits Using the Big-Batch Tensor Network Method",
        "venue": "Physical Review Letters",
        "citation": "Physical Review Letters 128, 030501 (2022)",
        "doi": "10.1103/PhysRevLett.128.030501",
        "doi_url": "https://doi.org/10.1103/PhysRevLett.128.030501",
        "locator": "030501"
      },
      "status": "Compute-bounded feature reproduction",
      "similarity_level": "numerical_feature_reproduction",
      "audit_score": 70.0,
      "summary": "Reproduces batch-probability, post-selection XEB, conditional-probability, and complexity-table features.",
      "limitation": "The exact 53-qubit contraction is not launched: the paper reports 4.51e18 head-contraction operations and 149 days on one A100, while a direct complex128 statevector would require 128 PiB. The public case also lacks the original circuit, contraction path, slicing configuration, and validation-amplitude bundle.",
      "run_scripts": [
        "run_reproduction.py",
        "plot_reproduction.py"
      ],
      "extra_dependencies": [],
      "comparison_attribution": "Pan and Zhang",
      "comparison_results": [
        {
          "paper_item": "Fig. 2",
          "figure": "fig2_depth20_porter_thomas_comparison.png"
        },
        {
          "paper_item": "Fig. 5",
          "figure": "fig5_depth14_porter_thomas_comparison.png"
        },
        {
          "paper_item": "Fig. 6",
          "figure": "fig6_conditional_probability_comparison.png"
        }
      ]
    },
    {
      "paper_id": "2512.23799",
      "title": "Efficient simulation of logical magic state preparation protocols",
      "topic": "Logical magic-state preparation simulation",
      "preprint": {
        "identifier": "arXiv:2512.23799",
        "title": "Efficient simulation of logical magic state preparation protocols",
        "url": "https://arxiv.org/abs/2512.23799"
      },
      "publication": {
        "status": "published",
        "title": "Efficient Simulation of Logical Magic State Preparation Protocols",
        "venue": "PRX Quantum",
        "citation": "PRX Quantum 7, 020329 (2026)",
        "doi": "10.1103/fby6-xjbm",
        "doi_url": "https://doi.org/10.1103/fby6-xjbm",
        "locator": "020329"
      },
      "status": "Exact-circuit partial reproduction",
      "similarity_level": "numerical_feature_reproduction",
      "audit_score": 73.0,
      "summary": "Reconstructs the exact Steane [[7,1,3]] logical-H circuit and evaluates acceptance, logical infidelity, runtime, and sampling precision.",
      "limitation": "Exact-circuit acceptance matches all 12 validated points, while mid-range logical infidelity remains 0.42-0.68x of the paper curve because the panel-(c) gate/idle schedule is reconstructed and the author implementation is unavailable. Runtime remains proxy timing; digitized source point sets are not redistributed.",
      "run_scripts": [
        "run_reproduction.py",
        "plot_reproduction.py",
        "run_steane_exact_benchmark.py",
        "plot_steane_exact_comparison.py"
      ],
      "script_arguments": {
        "run_steane_exact_benchmark.py": "--profile smoke"
      },
      "full_run_scripts": [
        "run_steane_exact_benchmark.py"
      ],
      "full_run_script_arguments": {
        "run_steane_exact_benchmark.py": "--profile paper"
      },
      "full_run_note": "The paper profile evaluates all 12 physical-error points with the larger Monte Carlo shot budget used by the published case output.",
      "extra_dependencies": [],
      "comparison_attribution": "Surti, Daguerre, and Kim",
      "comparison_results": [
        {
          "paper_item": "Fig. 1 (logical infidelity)",
          "figure": "fig1_infidelity_comparison.png"
        },
        {
          "paper_item": "Fig. 2 (acceptance rate)",
          "figure": "fig2_acceptance_comparison.png"
        },
        {
          "paper_item": "Fig. 3 (runtime)",
          "figure": "fig3_runtime_comparison.png"
        }
      ]
    },
    {
      "paper_id": "2604.08669",
      "title": "An Algorithm for Fast Assembling Large-Scale Defect-Free Atom Arrays",
      "topic": "Defect-free atom-array assembly",
      "preprint": {
        "identifier": "arXiv:2604.08669",
        "title": "An Algorithm for Fast Assembling Large-Scale Defect-Free Atom Arrays",
        "url": "https://arxiv.org/abs/2604.08669"
      },
      "publication": {
        "status": "not_recorded",
        "checked_at": "2026-07-14"
      },
      "status": "Paper-geometry partial reproduction",
      "similarity_level": "numerical_feature_reproduction",
      "audit_score": 61.6,
      "summary": "Reproduces paper-geometry path-planning probes, paper-scale P2WGS continuity, and a pipelined timing model for atom-array assembly.",
      "limitation": "The case includes an A100-SXM4-80GB 127x127 to 101x101 geometry probe and paper-scale P2WGS at N=10201. Full million-sample GNN training was stopped after the strict metric-contract gate failed; the unavailable GPU-parallel auction kernel is not replaced by CPU timing claims.",
      "run_scripts": [
        "run_reduced_pilot.py",
        "run_reduced_p2wgs_pilot.py",
        "plot_reduced_outputs.py",
        "plot_completion_summary.py"
      ],
      "extra_dependencies": [
        "torch"
      ]
    },
    {
      "paper_id": "2605.25398",
      "title": "Boson Sampling as a Probe of Chaotic and Integrable Quantum Dynamics",
      "topic": "Boson sampling and quantum-chaos probes",
      "preprint": {
        "identifier": "arXiv:2605.25398",
        "title": "Boson Sampling as a Probe of Chaotic and Integrable Quantum Dynamics in a Photonic Chip",
        "url": "https://arxiv.org/abs/2605.25398"
      },
      "publication": {
        "status": "not_recorded",
        "checked_at": "2026-07-14"
      },
      "status": "Feature-level reproduction",
      "similarity_level": "numerical_feature_reproduction",
      "audit_score": 79.36,
      "summary": "Reproduces Porter-Thomas distance, entropy, spectral-form-factor, OTOC, participation-ratio, and scaling features.",
      "limitation": "Several figures use paper-parameter subsets or local random-matrix instances rather than the full experimental setting.",
      "run_scripts": [
        "run_reproduction.py",
        "plot_reproduction.py"
      ],
      "extra_dependencies": [],
      "comparison_attribution": "Zhan et al.",
      "comparison_results": [
        {
          "paper_item": "Fig. 2 (g,h)",
          "figure": "fig2_output_distribution_comparison.png"
        },
        {
          "paper_item": "Fig. 3",
          "figure": "fig3_chaos_probes_comparison.png"
        },
        {
          "paper_item": "Fig. 4",
          "figure": "fig4_otoc_participation_comparison.png"
        },
        {
          "paper_item": "Fig. S1",
          "figure": "figS1_conditional_pt_comparison.png"
        },
        {
          "paper_item": "Fig. S4",
          "figure": "figS4_mode_scaling_comparison.png"
        },
        {
          "paper_item": "Fig. S5",
          "figure": "figS5_ideal_otocs_comparison.png"
        },
        {
          "paper_item": "Fig. S6",
          "figure": "figS6_otoc_spectrum_comparison.png"
        }
      ]
    },
    {
      "paper_id": "2605.25594",
      "title": "Sensitivity to perturbations in the three-dimensional Anderson model",
      "topic": "Three-dimensional Anderson localization",
      "preprint": {
        "identifier": "arXiv:2605.25594",
        "title": "Sensitivity to perturbations in the three-dimensional Anderson model",
        "url": "https://arxiv.org/abs/2605.25594"
      },
      "publication": {
        "status": "not_recorded",
        "checked_at": "2026-07-14"
      },
      "status": "Paper-scale subset reproduction",
      "similarity_level": "numerical_feature_reproduction",
      "audit_score": 67.49,
      "summary": "Reproduces disorder sensitivity, gap-ratio, IPR, susceptibility separation, and phenomenological strong-disorder trends, including an A100 campaign at L=24,28,31 with 605 disorder realizations.",
      "limitation": "The paper's L=32-38 targets were not forced through the current dense eigensolver: L=32 hit a 32-bit workspace failure and L=38 exceeds the practical single-A100 memory path. The T and randomized-site n operator panels remain outside the completed subset and are not replaced by proxy data.",
      "run_scripts": [
        "run_reproduction.py",
        "plot_reproduction.py",
        "run_fig11_phenomenological_model.py"
      ],
      "extra_dependencies": [],
      "comparison_attribution": "Tokarczyk et al.",
      "comparison_results": [
        {
          "paper_item": "Fig. 1",
          "figure": "fig1_fidelity_vs_disorder_comparison.png"
        },
        {
          "paper_item": "Fig. 2",
          "figure": "fig2_weak_crossover_scaling_comparison.png"
        },
        {
          "paper_item": "Fig. 3",
          "figure": "fig3_spectral_function_comparison.png"
        },
        {
          "paper_item": "Fig. 8",
          "figure": "fig8_typical_average_comparison.png"
        },
        {
          "paper_item": "Fig. 9",
          "figure": "fig9_chi_typ_comparison.png"
        }
      ]
    },
    {
      "paper_id": "2507.09447",
      "title": "Lyapunov formulation of band theory for disordered non-Hermitian systems",
      "topic": "Lyapunov band theory and the non-Hermitian skin–Anderson transition",
      "preprint": {
        "identifier": "arXiv:2507.09447",
        "title": "Lyapunov formulation of band theory for disordered non-Hermitian systems",
        "url": "https://arxiv.org/abs/2507.09447"
      },
      "publication": {
        "status": "published",
        "title": "Universal Thouless relations for disordered non–Hermitian systems in one dimension",
        "venue": "Science Bulletin",
        "citation": "Science Bulletin (2026), online ahead of print",
        "doi": "10.1016/j.scib.2026.05.055",
        "doi_url": "https://doi.org/10.1016/j.scib.2026.05.055",
        "locator": "PII S2095-9273(26)00583-9"
      },
      "status": "Paper-scale feature reproduction",
      "similarity_level": "numerical_feature_reproduction",
      "audit_score": 89.0,
      "summary": "Reproduces Figs. 3–5 with an L=1000, 3200-realization spectral ensemble, Lyapunov grids, state profiles, winding sectors, and the W_c=2.1 transition.",
      "limitation": "Author seeds, state-selection windows, transfer/grid details, and final artwork are unavailable; all scientific gates pass, but source-pixel identity is not claimed. This is an author-protocol boundary, not a compute boundary, so no further large campaign is scheduled.",
      "run_scripts": [
        "plot_paper_exact.py",
        "qa_paper_exact.py"
      ],
      "full_run_scripts": [
        "run_paper_exact.py"
      ],
      "full_run_note": "The full L=1000, 3200-realization rerun is resumable but computationally expensive; the quick commands regenerate figures and scientific checks from the published generated data.",
      "featured_results": [
        {
          "paper_item": "Fig. 3",
          "result": "OBC spectral density, state profiles, mobility edge, and scaling",
          "figure": "fig3_paper_exact.png",
          "check": "paper_scientific_similarity.json"
        },
        {
          "paper_item": "Fig. 4",
          "result": "PBC spectral density and winding sectors",
          "figure": "fig4_paper_exact.png",
          "check": "paper_scientific_similarity.json"
        },
        {
          "paper_item": "Fig. 5",
          "result": "Mobility-contour shrinkage and the skin–Anderson transition",
          "figure": "fig5_paper_exact.png",
          "check": "paper_scientific_similarity.json"
        }
      ],
      "extra_dependencies": [],
      "comparison_attribution": "Sun and Hu",
      "comparison_results": [
        {
          "paper_item": "Fig. 3",
          "figure": "fig3_obc_spectrum_comparison.png"
        },
        {
          "paper_item": "Fig. 4",
          "figure": "fig4_pbc_winding_comparison.png"
        },
        {
          "paper_item": "Fig. 5",
          "figure": "fig5_skin_anderson_comparison.png"
        }
      ]
    },
    {
      "paper_id": "10.1007-s11433-024-2478-8",
      "title": "Buffer-atom-mediated quantum logic gates with off-resonant modulated driving",
      "topic": "Buffer-atom-mediated Rydberg CZ, dual-pulse Doppler upgrade, and amplitude-ratio robustness via off-resonant modulated driving",
      "preprint": {
        "status": "not_recorded",
        "checked_at": "2026-07-14"
      },
      "publication": {
        "status": "published",
        "title": "Buffer-atom-mediated quantum logic gates with off-resonant modulated driving",
        "venue": "Science China Physics, Mechanics & Astronomy",
        "citation": "Sci. China-Phys. Mech. Astron. 67, 120311 (2024)",
        "doi": "10.1007/s11433-024-2478-8",
        "doi_url": "https://doi.org/10.1007/s11433-024-2478-8",
        "locator": "Article 120311"
      },
      "status": "Mixed: Fig. 3 complete, Fig. 4/5/7 feature-level",
      "similarity_level": "numerical_feature_reproduction",
      "audit_score": 84.6,
      "summary": "Reproduces the buffer-atom-mediated CZ gate from an independent three-body Rydberg Hamiltonian: single-photon waveforms, populations, and phases (Fig. 3, complete, gate error < 1e-4), the two-photon protocol (Fig. 4), the Doppler-insensitive dual-pulse upgrade (Fig. 5), and the amplitude-ratio robustness map (Fig. 7).",
      "limitation": "The two-photon full three-level model gives gate error ~1e-3 vs the paper's <1e-4 (its waveforms were likely optimised in a reduced/effective model); Fig. 7 peak ~25% below the paper; Fig. 6 three-qubit Toffoli geometry is underspecified and not reproduced; Figs. a6-a8 have no published coefficients.",
      "run_scripts": [
        "run_fig3.py",
        "run_fig4.py",
        "run_fig5.py",
        "run_fig7.py"
      ],
      "full_run_scripts": [],
      "full_run_note": "All figures run on a laptop CPU (Fig. 3 in seconds; Fig. 4/5 ~1 min; Fig. 7 a few min across cores). No GPU or cluster needed.",
      "comparison_attribution": "Y. Sun",
      "comparison_results": [
        {
          "paper_item": "Fig. 3 (single-photon CZ)",
          "figure": "fig3_singlephoton_comparison.png"
        },
        {
          "paper_item": "Fig. 4 (two-photon CZ)",
          "figure": "fig4_twophoton_comparison.png"
        },
        {
          "paper_item": "Fig. 5 (dual-pulse Doppler)",
          "figure": "fig5_dualpulse_comparison.png"
        },
        {
          "paper_item": "Fig. 7 (robustness colormap)",
          "figure": "fig7_robustness_comparison.png"
        }
      ]
    },
    {
      "paper_id": "10.1103-PhysRevB.91.085420",
      "title": "Interband coherence induced correction to adiabatic pumping in periodically driven systems",
      "topic": "Interband-coherence correction to adiabatic pumping in the continuously driven Harper model",
      "preprint": {
        "status": "not_recorded",
        "checked_at": "2026-07-14"
      },
      "publication": {
        "status": "published",
        "title": "Interband coherence induced correction to adiabatic pumping in periodically driven systems",
        "venue": "Physical Review B",
        "citation": "Physical Review B 91, 085420 (2015)",
        "doi": "10.1103/PhysRevB.91.085420",
        "doi_url": "https://doi.org/10.1103/PhysRevB.91.085420",
        "locator": "085420"
      },
      "status": "Feature-level reproduction",
      "similarity_level": "numerical_feature_reproduction",
      "audit_score": 79.54,
      "summary": "Independently reproduces all four figures of the continuously driven Harper model pumping study: the Floquet spectrum and initial populations, the one-cycle population change from exact dynamics versus Eq. (8), the T-independent wave-packet displacement, and the topological-transition probe -- confirming that the Berry-only term is wrong and the interband-coherence correction of Eq. (13) is essential.",
      "limitation": "Comparison is a source-vs-reproduction feature contract against the paper's raster figures (no author data or tables); Fig. 2 is feature-level due to the intrinsic ~10^2-rad phase sensitivity of Eq. (8) at T=1024, and the Fig. 4 actual peak sits below the paper value in the narrow band-touching window where the dynamics is genuinely T-sensitive.",
      "run_scripts": [
        "run_fig1.py",
        "run_fig2.py",
        "run_fig3.py",
        "run_fig4.py"
      ],
      "extra_dependencies": [],
      "featured_results": [
        {
          "paper_item": "Fig. 1",
          "result": "Floquet spectrum omega(k,beta) and initial band populations, J=K=3",
          "figure": "fig1_reproduction.png",
          "check": "fig1.json"
        },
        {
          "paper_item": "Fig. 2",
          "result": "One-cycle population change Delta rho: exact dynamics vs Eq. (8), J=K=3, T=1024",
          "figure": "fig2_reproduction.png",
          "check": "fig2.json"
        },
        {
          "paper_item": "Fig. 3",
          "result": "T-independent wave-packet displacement <x>(t); Eq. (13) total vs Berry-only, J=K=4",
          "figure": "fig3_reproduction.png",
          "check": "fig3.json"
        },
        {
          "paper_item": "Fig. 4",
          "result": "Delta<x> vs J across the Floquet-Chern transition; actual vs Eq. (13) vs Berry-only",
          "figure": "fig4_reproduction.png",
          "check": "fig4.json"
        }
      ],
      "comparison_attribution": "Wang, Zhou, and Gong",
      "comparison_results": [
        {
          "paper_item": "Fig. 1",
          "figure": "fig1_spectrum_populations_comparison.png"
        },
        {
          "paper_item": "Fig. 2",
          "figure": "fig2_delta_rho_comparison.png"
        },
        {
          "paper_item": "Fig. 3",
          "figure": "fig3_displacement_comparison.png"
        },
        {
          "paper_item": "Fig. 4",
          "figure": "fig4_transition_probe_comparison.png"
        }
      ]
    },
    {
      "paper_id": "10.1038-s41586-024-08262-7",
      "title": "Particle exchange statistics beyond fermions and bosons",
      "topic": "Paraparticle exclusion statistics, thermodynamics, and exactly solvable spin models",
      "preprint": {
        "identifier": "arXiv:2308.05203",
        "title": "Particle exchange statistics beyond fermions and bosons",
        "url": "https://arxiv.org/abs/2308.05203"
      },
      "publication": {
        "status": "published",
        "title": "Particle exchange statistics beyond fermions and bosons",
        "venue": "Nature",
        "citation": "Nature 637, 314–318 (2025)",
        "doi": "10.1038/s41586-024-08262-7",
        "doi_url": "https://doi.org/10.1038/s41586-024-08262-7",
        "locator": "314–318"
      },
      "status": "Complete reproduction",
      "similarity_level": "complete_reproduction",
      "audit_score": 90.0,
      "summary": "Reproduces the numerical main figure from the paper's closed-form single-mode statistics at the published legend parameters, and independently validates the free-paraparticle spectrum of the one-dimensional solvable spin model by exact diagonalization.",
      "limitation": "The Nature figure is raster-only and no author plotting-data table is available, so the comparison tier is analytic-reference rather than author-data pointwise. The two-dimensional KDH model, eight-body plaquette terms, and braiding demonstration are outside this case's scope.",
      "run_scripts": [
        "gen_fig2.py",
        "run_ed_validation.py"
      ],
      "extra_dependencies": [],
      "additional_resources": [
        {
          "label": "中文逐步推导",
          "path": "docs/DERIVATION_WALKTHROUGH.zh-CN.md"
        },
        {
          "label": "中文推导讲义 PDF",
          "path": "docs/DERIVATION_WALKTHROUGH.zh-CN.pdf"
        }
      ],
      "featured_results": [
        {
          "paper_item": "Numerical main figure",
          "result": "Generalized exclusion statistics and free-paraparticle thermodynamics",
          "figure": "fig2_reproduction.png",
          "check": "fig2.json"
        }
      ]
    },
    {
      "paper_id": "10.1126-science.aaw1611",
      "title": "Strongly correlated quantum walks with a 12-qubit superconducting processor",
      "topic": "Strongly interacting one- and two-photon quantum walks on a calibrated superconducting-qubit chain",
      "preprint": {
        "status": "not_recorded",
        "checked_at": "2026-07-15"
      },
      "publication": {
        "status": "published",
        "title": "Strongly correlated quantum walks with a 12-qubit superconducting processor",
        "venue": "Science",
        "citation": "Science 364, 753–756 (2019)",
        "doi": "10.1126/science.aaw1611",
        "doi_url": "https://doi.org/10.1126/science.aaw1611",
        "locator": "753–756"
      },
      "status": "Pixel-audited numerical feature reproduction",
      "similarity_level": "numerical_feature_reproduction",
      "audit_score": 80.0,
      "summary": "Independently reproduces the calibrated one- and two-photon Bose–Hubbard dynamics, information-spreading observables, interaction-induced antibunching, and double-occupancy suppression. A supplemental scalar-field pixel audit covers the theoretical interiors of Figs. S14–S20.",
      "limitation": "Author theory tables, experimental shots, and tomography arrays are unavailable. Publisher rasters are used only for internal validation and are not redistributed; the S20 correlator audit remains visibly weaker than the density panels.",
      "run_scripts": [
        "run_reproduction.py"
      ],
      "extra_dependencies": [],
      "featured_results": [
        {
          "paper_item": "Fig. 2D–F / Figs. S14–S16",
          "result": "Calibrated one-photon density from Q6, Q1, and Q11 launches",
          "figure": "S14_density_Q6.png",
          "check": "T001_checks.json"
        },
        {
          "paper_item": "Fig. 3B–E / Fig. S17",
          "result": "One-site entropy and information spreading from a Q6 launch",
          "figure": "S17_entropy_Q6.png",
          "check": "T002_checks.json"
        },
        {
          "paper_item": "Fig. 4 / Figs. S19–S20",
          "result": "Two-photon density and correlator fermionization against free and hard-core controls",
          "figure": "S20_two_particle_correlator_theory.png",
          "check": "T003_checks.json"
        },
        {
          "paper_item": "Fig. S8",
          "result": "Site-resolved suppression of double occupancy",
          "figure": "S8_double_occupancy.png",
          "check": "T004_checks.json"
        }
      ]
    },
    {
      "paper_id": "10.1038-s41586-026-10720-3",
      "title": "Backreaction of stimulated Hawking radiation in an optical analogue",
      "topic": "Stimulated Hawking radiation and backreaction in a fibre-optical analogue horizon",
      "preprint": {
        "identifier": "arXiv:2607.01118",
        "title": "Backreaction of stimulated Hawking radiation in an optical analogue",
        "url": "https://arxiv.org/abs/2607.01118"
      },
      "publication": {
        "status": "published",
        "title": "Backreaction of stimulated Hawking radiation in an optical analogue",
        "venue": "Nature",
        "citation": "Nature 655, 336-341 (2026)",
        "doi": "10.1038/s41586-026-10720-3",
        "doi_url": "https://doi.org/10.1038/s41586-026-10720-3",
        "locator": "336-341"
      },
      "status": "Main-figure numerical feature reproduction",
      "similarity_level": "numerical_feature_reproduction",
      "audit_score": 78.47,
      "summary": "Without author code, reproduces the numerical content and registered layout of main-text Figs. 2, 4, and 5: seven phase-matching landmarks, all six Eq. (D.1) spectra, and the 1.0211 thermal-slope ratio.",
      "limitation": "The measured fibre coefficients, raw spectra, fitted parameter tables, raw NRR fluxes, and measured pulse shapes are unavailable; visible PDF vector content is used internally as a source-derived fit or validation input, so this is not author-data-level exact reproduction.",
      "run_scripts": [
        "run_main_figures.py"
      ],
      "extra_dependencies": [
        "torch"
      ],
      "featured_results": [
        {
          "paper_item": "Fig. 2",
          "result": "Co-moving dispersion and seven phase-matching landmarks",
          "figure": "fig2_doppler_reproduction_public.png",
          "check": "main_figure_reproduction.json"
        },
        {
          "paper_item": "Fig. 4",
          "result": "Six independently evaluated Eq. (D.1) theory spectra",
          "figure": "fig4_eq_d1_theory_public.png",
          "check": "main_figure_reproduction.json"
        },
        {
          "paper_item": "Fig. 5",
          "result": "Public-safe Eq. (D.3) fitted lines with slope ratio 1.0211",
          "figure": "fig5_eq_d3_lines_public.png",
          "check": "main_figure_reproduction.json"
        }
      ],
      "comparison_attribution": "Procopio et al.",
      "comparison_note": "The left column is a limited paper excerpt. The right column is the case reconstruction: its theory curves, roots, and regressions are equation-generated, while the displayed Fig. 4/5 markers are disclosed source-derived fit or regression inputs. The boards validate structure and numerical features, not author-data-level independence.",
      "comparison_results": [
        {
          "paper_item": "Fig. 2",
          "figure": "fig2_pixel_comparison.png"
        },
        {
          "paper_item": "Fig. 4",
          "figure": "fig4_pixel_comparison.png"
        },
        {
          "paper_item": "Fig. 5",
          "figure": "fig5_pixel_comparison.png"
        }
      ]
    },
    {
      "paper_id": "10.1103-PRXQuantum.6.010331",
      "title": "Benchmarking and Fidelity Response Theory of High-Fidelity Rydberg Entangling Gates",
      "topic": "Fidelity-response theory and protocol-level noise susceptibility of high-fidelity Rydberg CZ gates",
      "preprint": {
        "identifier": "arXiv:2407.20184",
        "title": "Benchmarking and Fidelity Response Theory of High-Fidelity Rydberg Entangling Gates",
        "url": "https://arxiv.org/abs/2407.20184"
      },
      "publication": {
        "status": "published",
        "title": "Benchmarking and Fidelity Response Theory of High-Fidelity Rydberg Entangling Gates",
        "venue": "PRX Quantum",
        "citation": "PRX Quantum 6, 010331 (2025)",
        "doi": "10.1103/PRXQuantum.6.010331",
        "doi_url": "https://doi.org/10.1103/PRXQuantum.6.010331",
        "locator": "010331"
      },
      "status": "Formula-derived numerical reproduction",
      "similarity_level": "numerical_feature_reproduction",
      "audit_score": 79.89,
      "summary": "Reproduces all nine theory targets closed by printed formulas and public control parameters: Appendix-L universal responses and scaling, error and principal-quantum-number laws, three protocol-level CZ responses, spin-lock and cavity filters, the phase-flip/SSB model, and a seven-site many-body response. Every dataset is generated from formulas or Hamiltonian propagation; no source-figure pixels enter computation.",
      "limitation": "The 79.89 score covers only T001-T002, which have paper-exact analytic references. Exact absolute curves that require unreleased PSD or calibration arrays, target-specific pulse/ramp identity, atomic geometry, or discrete circuit metadata remain explicitly partial or reconstructed and were not filled by tracing paper figures.",
      "run_scripts": [
        "run_reproduction.py",
        "run_formula_theory_targets.py"
      ],
      "extra_dependencies": [],
      "featured_results": [
        {
          "paper_item": "Fig. 15",
          "result": "Universal Haar and symmetric-Haar frequency/intensity responses from Appendix-L formulas",
          "figure": "fig15_universal_response.png",
          "check": "universal_response.json"
        },
        {
          "paper_item": "Fig. 6(a)",
          "result": "Dimensional response scaling at 3.0 and 7.7 MHz with universal-collapse verification",
          "figure": "fig6a_scaled_response.png",
          "check": "fig6a_scaled_response.json"
        },
        {
          "paper_item": "Fig. 9(a,b)",
          "result": "Independent eight-dimensional Hamiltonian responses for three Rydberg CZ protocols",
          "figure": "fig9_protocol_responses.png",
          "check": "formula_theory_targets.json"
        },
        {
          "paper_item": "Fig. 11",
          "result": "Independent seven-site, 128-dimensional quench and quasi-adiabatic response reconstruction",
          "figure": "fig11_many_body_responses.png",
          "check": "formula_theory_targets.json"
        },
        {
          "paper_item": "Fig. 17",
          "result": "Phase-flip fidelity polynomials and first-order symmetric-stabilizer cancellation",
          "figure": "fig17_phase_flip_first_order.png",
          "check": "formula_theory_targets.json"
        }
      ],
      "comparison_attribution": "Tsai et al.",
      "comparison_results": [
        {
          "paper_item": "Fig. 15",
          "figure": "fig15_response_comparison.png"
        },
        {
          "paper_item": "Fig. 6(a)",
          "figure": "fig6_response_comparison.png"
        }
      ]
    },
    {
      "paper_id": "10.1103-PhysRevLett.124.113601",
      "title": "Localization Driven Superradiant Instability",
      "topic": "Aubry–André localization, cavity susceptibility, and superradiant instability",
      "preprint": {
        "identifier": "arXiv:1909.08125",
        "title": "Localization Driven Superradiant Instability",
        "url": "https://arxiv.org/abs/1909.08125"
      },
      "publication": {
        "status": "published",
        "title": "Localization Driven Superradiant Instability",
        "venue": "Physical Review Letters",
        "citation": "Physical Review Letters 124, 113601 (2020)",
        "doi": "10.1103/PhysRevLett.124.113601",
        "doi_url": "https://doi.org/10.1103/PhysRevLett.124.113601",
        "locator": "113601"
      },
      "status": "Pixel-registered numerical feature reproduction",
      "similarity_level": "numerical_feature_reproduction",
      "audit_score": 88.56,
      "summary": "Independently reproduces Figs. 2–4 and Supplement Fig. S1 from AA/GAA and cavity mean-field numerics, including a complete Fig. 3 reproduction, a 377-point IPR match, nonlinear photon onset, and pixel-registered paper geometry.",
      "limitation": "Only Fig. 3 is final-reproduction eligible. Fig. 2 omits the excited-state threshold normalization, Fig. 4 has a published/arXiv detuning-convention split, and Fig. S1 omits pump samples and iterative-solver metadata.",
      "run_scripts": [
        "run_linear_targets.py",
        "run_nonlinear_targets.py",
        "render_pixel_registered.py"
      ],
      "extra_dependencies": [],
      "featured_results": [
        {
          "paper_item": "Fig. 2",
          "result": "Mobility-edge IPR and state-resolved threshold",
          "figure": "fig2_pixel_registered.png",
          "check": "fig2_state_thresholds.json"
        },
        {
          "paper_item": "Fig. 3",
          "result": "Susceptibility and momentum-scattering mechanism",
          "figure": "fig3_pixel_registered.png",
          "check": "fig3_mechanism.json"
        },
        {
          "paper_item": "Fig. 4",
          "result": "Nonlinear photon onset and critical-pump landscape",
          "figure": "fig4_pixel_registered.png",
          "check": "fig4a_photon_number.json"
        },
        {
          "paper_item": "Fig. S1",
          "result": "Self-consistent normal and superradiant density profiles",
          "figure": "figs1_pixel_registered.png",
          "check": "figs1_density_profiles.json"
        }
      ],
      "comparison_attribution": "Yin et al.",
      "comparison_note": "Each board uses a limited attributed paper excerpt as an audit reference, an independently generated numerical render, and an absolute-pixel-difference panel. Reference pixels and PDF vectors do not enter the numerical model or generated image.",
      "comparison_results": [
        {
          "paper_item": "Fig. 3",
          "figure": "fig3_pixel_difference.png"
        },
        {
          "paper_item": "Fig. 4",
          "figure": "fig4_pixel_difference.png"
        },
        {
          "paper_item": "Fig. S1",
          "figure": "figs1_pixel_difference.png"
        }
      ]
    },
    {
      "paper_id": "2607.02157",
      "title": "Thermodynamics of Quantum Reservoir Computing",
      "topic": "Non-equilibrium thermodynamic limits of driven open quantum reservoirs; generalized Landauer bound and information-dissipation identity",
      "preprint": {
        "status": "recorded",
        "identifier": "arXiv:2607.02157",
        "title": "Thermodynamics of Quantum Reservoir Computing",
        "url": "https://arxiv.org/abs/2607.02157"
      },
      "publication": {
        "status": "not_recorded",
        "checked_at": "2026-07-20"
      },
      "status": "Feature-level reproduction (paper-exact ensembles)",
      "similarity_level": "numerical_feature_reproduction",
      "audit_score": 79.18,
      "summary": "Independently reproduces all three numerical figures of Ding & Qiu's thermodynamics of quantum reservoir computing at the paper's full ensemble sizes: the memory/predictive Holevo capacities, generalized Landauer bound, and coherence decomposition (Fig. 2, both TFIM and cluster architectures), the drive spectral resonance G(omega) and reservoir spectra (Fig. S1), and the multi-step capacities with forecasting error (Fig. S2). The central identity beta*W_irr = chi^d (Eq. 13) holds at machine precision across all runs, and the capacity peaks and NMSE minima coincide inside the quantum critical regions.",
      "limitation": "Comparison is a feature contract against the paper's raster panels (no author data or tables); score is bound at 80 because the paper releases no numerical data and we decline to digitize its curves. The disorder-ensemble aggregation convention (per-realization vs pooled) was adjudicated to resolve a TFIM peak ambiguity; three unspecified conventions (Mackey-Glass normalization, cluster boundary condition, F(omega) normalization) are documented as questions for the authors.",
      "run_scripts": [
        "run_scan.py",
        "run_nmse.py",
        "run_figS1.py",
        "plot_figures.py",
        "adjudicate_pooling.py",
        "verify_formulas.py"
      ],
      "extra_dependencies": [],
      "featured_results": [
        {
          "paper_item": "Fig. 2",
          "result": "Holevo capacities, generalized Landauer bound, coherence decomposition; TFIM and cluster, paper-exact ensembles",
          "figure": "fig2_reproduction.png",
          "check": "fig2_figS2_feature_contract.json"
        },
        {
          "paper_item": "Fig. S1",
          "result": "Drive resonance G(omega) peak and TFIM/cluster reservoir spectra",
          "figure": "figS1_reproduction.png",
          "check": "figS1_features.json"
        },
        {
          "paper_item": "Fig. S2",
          "result": "Multi-step memory/predictive capacities and full-Pauli NMSE minima",
          "figure": "figS2_reproduction.png",
          "check": "fig2_figS2_feature_contract.json"
        }
      ],
      "comparison_attribution": "Ding and Qiu",
      "comparison_results": [
        {
          "paper_item": "Fig. 2",
          "figure": "fig2_comparison.png"
        },
        {
          "paper_item": "Fig. S1",
          "figure": "figS1_comparison.png"
        },
        {
          "paper_item": "Fig. S2",
          "figure": "figS2_comparison.png"
        }
      ]
    },
    {
      "paper_id": "2407.01296",
      "title": "Geometry-adaptive formulation of non-Bloch bands in arbitrary dimensions and spectral instability",
      "topic": "Geometry-adaptive non-Bloch bands, non-Hermitian skin effect, and spectral instability",
      "preprint": {
        "identifier": "arXiv:2407.01296",
        "title": "Non-Hermitian skin effect in arbitrary dimensions: non-Bloch band theory and classification",
        "url": "https://arxiv.org/abs/2407.01296"
      },
      "publication": {
        "status": "published",
        "title": "Geometry-adaptive formulation of non-Bloch bands in arbitrary dimensions and spectral instability",
        "venue": "Communications Physics",
        "citation": "Communications Physics 9, 127 (2026)",
        "doi": "10.1038/s42005-026-02546-2",
        "doi_url": "https://doi.org/10.1038/s42005-026-02546-2",
        "locator": "Article 127"
      },
      "status": "Main-text scientific reproduction; pixel-registered, not identical",
      "similarity_level": "numerical_feature_reproduction",
      "audit_score": 88.39,
      "summary": "Completes the main-text scientific evidence chain for Figs. 1-5. Figs. 2(a-c), 3, and 4(a-f) are independently recomputed; Fig. 2(d) is author-data-assisted; Figs. 1 and 5 are analytic redraws. Every formal canvas is registered, while strict SSIM 0.95 pixel identity is explicitly not claimed.",
      "limitation": "Supplementary Figs. S2 and S4-S7 are not independently complete. Fig. 2(d) uses author-released ED tables, and unreported state selection, integer boundary vertices, random seeds, probe grids, three-dimensional projection, and renderer details limit pixel identity in Fig. 3 and several Fig. 4 panels.",
      "run_scripts": [
        "run_reproduction_smoke.py"
      ],
      "extra_dependencies": [],
      "featured_results": [
        {
          "paper_item": "Fig. 1",
          "result": "Analytic geometry-adaptive spectral-potential schematic",
          "figure": "fig1_pixel_registered.png",
          "check": "main_schematic_pixel_similarity.json"
        },
        {
          "paper_item": "Fig. 2",
          "result": "Geometry-dependent spectra, skin density, potential, and finite-size convergence",
          "figure": "fig2_full_pixel_registered.png",
          "check": "fig2_full_pixel_similarity.json"
        },
        {
          "paper_item": "Fig. 3",
          "result": "Geometry-dependent generalized Brillouin zones with corrected projection and view",
          "figure": "fig3_gbz_pixel_registered.png",
          "check": "fig3_gbz_pixel_similarity.json"
        },
        {
          "paper_item": "Fig. 4(a-f)",
          "result": "Critical boundary modes and spectral instability across all six panels",
          "figure": "fig4_full_pixel_registered.png",
          "check": "fig4_full_pixel_similarity.json"
        },
        {
          "paper_item": "Fig. 5",
          "result": "Analytic basis-transformation schematic",
          "figure": "fig5_pixel_registered.png",
          "check": "main_schematic_pixel_similarity.json"
        }
      ],
      "comparison_attribution": "Xing, Xiong, and Hu",
      "comparison_note": "Each board contains a limited attributed excerpt from the formal paper beside the independently generated registered result. The excerpts are used only for presentation audit; no reference pixels enter numerical computation. The boards demonstrate remaining differences and do not assert pixel identity.",
      "comparison_results": [
        {
          "paper_item": "Fig. 1",
          "figure": "fig1_pixel_comparison.png"
        },
        {
          "paper_item": "Fig. 2",
          "figure": "fig2_full_pixel_comparison.png"
        },
        {
          "paper_item": "Fig. 3",
          "figure": "fig3_gbz_pixel_comparison.png"
        },
        {
          "paper_item": "Fig. 4",
          "figure": "fig4_full_pixel_comparison.png"
        },
        {
          "paper_item": "Fig. 5",
          "figure": "fig5_pixel_comparison.png"
        }
      ]
    }
  ]
}
